eleanor/__init__.py
eleanor/crossmatch.py
eleanor/eleanor.py
eleanor/ffi.py
eleanor/mast.py
eleanor/maxsector.py
eleanor/models.py
eleanor/postcard.py
eleanor/postcard_centers.txt
eleanor/source.py
eleanor/targetdata.py
eleanor/update.py
eleanor/utils.py
eleanor/version.py
eleanor/visualize.py
eleanor_mamu-1.0.2.dist-info/LICENSE
eleanor_mamu-1.0.2.dist-info/METADATA
eleanor_mamu-1.0.2.dist-info/WHEEL
eleanor_mamu-1.0.2.dist-info/top_level.txt
eleanor_mamu-1.0.2.dist-info/RECORD
