Metadata-Version: 2.1
Name: eleanor-mamu
Version: 1.0.2
Summary: Source Extraction for TESS Full Frame Images
Home-page: http://github.com/afeinstein20/eleanor
Author: Adina D. Feinstein
Author-email: adina.d.feinstein@gmail.com
License: MIT
Platform: UNKNOWN
Classifier: Development Status :: 3 - Alpha
Classifier: Intended Audience :: Science/Research
Classifier: License :: OSI Approved :: MIT License
Classifier: Operating System :: OS Independent
Classifier: Programming Language :: Python :: 3.0
Requires-Dist: photutils (>=0.7)
Requires-Dist: tqdm
Requires-Dist: lightkurve (>=1.1.0)
Requires-Dist: astropy (>=3.2.3)
Requires-Dist: astroquery
Requires-Dist: pandas
Requires-Dist: setuptools (>=41.0.0)
Requires-Dist: tensorflow (<=1.14.0)
Requires-Dist: vaneska
Requires-Dist: beautifulsoup4 (>=4.6.0)
Requires-Dist: tess-point (>=0.3.6)
